damagefunctions/__init__.py
damagefunctions/damagefunctions.py
damagefunctions-0.0.1.dist-info/METADATA
damagefunctions-0.0.1.dist-info/WHEEL
damagefunctions-0.0.1.dist-info/top_level.txt
damagefunctions-0.0.1.dist-info/RECORD
