Metadata-Version: 2.1
Name: damagefunctions
Version: 0.0.1
Summary: Flood residential damage functions
Home-page: https://github.com/pypa/sampleproject
Author: Pranavesh Panakkal, Jamie E. Padgett
Author-email: ppranavesh@gmail.com
License: UNKNOWN
Platform: UNKNOWN
Classifier: Programming Language :: Python :: 3
Classifier: License :: OSI Approved :: MIT License
Classifier: Operating System :: OS Independent
Requires-Python: >=3.6
